itermore/__init__.py
itermore-0.1.2.dist-info/DESCRIPTION.rst
itermore-0.1.2.dist-info/METADATA
itermore-0.1.2.dist-info/RECORD
itermore-0.1.2.dist-info/WHEEL
itermore-0.1.2.dist-info/metadata.json
itermore-0.1.2.dist-info/top_level.txt
