Metadata-Version: 2.0
Name: itermore
Version: 0.1.2
Summary: Additional function(s) to itertools: partial permutation
Home-page: http://github.com/atinzad/itermore
Author: Ahmad Albaqsami
Author-email: ahmad_baq@hotmail.com
License: MIT
Platform: UNKNOWN
